README.rst
setup.py
dj_pq/__init__.py
dj_pq.egg-info/PKG-INFO
dj_pq.egg-info/SOURCES.txt
dj_pq.egg-info/dependency_links.txt
dj_pq.egg-info/not-zip-safe
dj_pq.egg-info/requires.txt
dj_pq.egg-info/top_level.txt
dj_pq/management/__init__.py
dj_pq/management/commands/__init__.py
dj_pq/management/commands/worker.py
dj_pq/migrations/0001_initial.py
dj_pq/migrations/__init__.py
dj_pq/tests/__init__.py
dj_pq/tests/settings.py
dj_pq/tests/tests.py