Metadata-Version: 1.1
Name: dj-pq
Version: 1.4.2
Summary: ``pq`` wrapper for django
Home-page: https://github.com/jeanphix/dj-pq/
Author: jean-philippe serafin
Author-email: serafinjp@gmail.com
License: BSD License
Platform: any
Classifier: Development Status :: 5 - Production/Stable
Classifier: Intended Audience :: Developers
Classifier: Intended Audience :: Information Technology
Classifier: Intended Audience :: Science/Research
Classifier: Intended Audience :: System Administrators
Classifier: License :: OSI Approved :: BSD License
Classifier: Operating System :: POSIX
Classifier: Programming Language :: Python
Classifier: Topic :: Software Development :: Libraries :: Python Modules
Classifier: Topic :: Internet
Classifier: Topic :: System :: Distributed Computing
Classifier: Topic :: System :: Systems Administration
